bottle_werkzeug.py
bottle_werkzeug-0.1.1.dist-info/DESCRIPTION.rst
bottle_werkzeug-0.1.1.dist-info/METADATA
bottle_werkzeug-0.1.1.dist-info/RECORD
bottle_werkzeug-0.1.1.dist-info/WHEEL
bottle_werkzeug-0.1.1.dist-info/metadata.json
bottle_werkzeug-0.1.1.dist-info/top_level.txt
