Metadata-Version: 2.0
Name: bottle-werkzeug
Version: 0.1.1
Summary: Werkzeug integration for Bottle.
Home-page: https://github.com/bottlepy/bottle-werkzeug
Author: Marcel Hellkamp
Author-email: marc@gsites.de
License: MIT
Platform: any
Classifier: Environment :: Web Environment
Classifier: Intended Audience :: Developers
Classifier: License :: OSI Approved :: MIT License
Classifier: Operating System :: OS Independent
Classifier: Programming Language :: Python
Classifier: Topic :: Internet :: WWW/HTTP :: Dynamic Content
Classifier: Topic :: Software Development :: Libraries :: Python Modules
Classifier: Framework :: Bottle
Requires-Dist: bottle (>=0.9)
Requires-Dist: werkzeug
